gigawave/__init__.py
gigawave/exceptions.py
gigawave-1.0.7.dist-info/METADATA
gigawave-1.0.7.dist-info/WHEEL
gigawave-1.0.7.dist-info/licenses/LICENSE
gigawave-1.0.7.dist-info/RECORD
