Metadata-Version: 2.3
Name: gigawave
Version: 1.0.7
Summary: Official Python SDK for GigaWave™ 6000-Series Oscilloscopes.
Project-URL: Homepage, https://github.com/SJL-Instruments/GigaWave-SDK
Author-email: Samuel Li <samuel@sjl-instruments.com>
License-File: LICENSE
Classifier: License :: OSI Approved :: MIT License
Classifier: Operating System :: OS Independent
Classifier: Programming Language :: Python :: 3
Requires-Python: >=3.8
Requires-Dist: numpy>=1.21.0
Requires-Dist: pyserial>=3.2
Requires-Dist: scipy>=1.5.0
